streamlit_tailwind/__init__.py
streamlit_tailwind/frontend/index.html
streamlit_tailwind/frontend/main.js
streamlit_tailwind/frontend/streamlit-component-lib.js
streamlit_tailwind/frontend/style.css
streamlit_tailwind-0.1.0.dist-info/LICENSE
streamlit_tailwind-0.1.0.dist-info/METADATA
streamlit_tailwind-0.1.0.dist-info/WHEEL
streamlit_tailwind-0.1.0.dist-info/top_level.txt
streamlit_tailwind-0.1.0.dist-info/RECORD
