Metadata-Version: 2.1
Name: streamlit-tailwind
Version: 0.1.0
Summary: A streamlit component that allows the addition of custom HTML with Tailwind classes
Author: Kevin Ongko
Author-email:  
Requires-Python: >=3.7
License-File: LICENSE
